food_inventory_x24148385_pkg/__init__.py
food_inventory_x24148385_pkg/low_stock.py
food_inventory_x24148385-0.0.1.dist-info/METADATA
food_inventory_x24148385-0.0.1.dist-info/WHEEL
food_inventory_x24148385-0.0.1.dist-info/licenses/LICENSE
food_inventory_x24148385-0.0.1.dist-info/RECORD
