Metadata-Version: 2.4
Name: food_inventory_x24148385
Version: 0.0.1
Summary: A small package to check low inventory
Project-URL: Homepage, https://github.com/pypa/food_inventory_x24148385
Project-URL: Bug Tracker, https://github.com/pypa/food_inventory_x24148385/issues
Author-email: Maaz Ahmed <x24148385@student.ncirl.ie>
License-File: LICENSE
Classifier: License :: OSI Approved :: MIT License
Classifier: Operating System :: OS Independent
Classifier: Programming Language :: Python :: 3
Requires-Python: >=3.9
